jax_nca/__init__.py
jax_nca/dataset.py
jax_nca/nca.py
jax_nca/trainer.py
jax_nca/utils.py
jax_nca-0.1.2.dist-info/LICENSE
jax_nca-0.1.2.dist-info/METADATA
jax_nca-0.1.2.dist-info/WHEEL
jax_nca-0.1.2.dist-info/top_level.txt
jax_nca-0.1.2.dist-info/RECORD
