Metadata-Version: 2.1
Name: jax-nca
Version: 0.1.2
Summary: Neural Cellular Automata (https://distill.pub/2020/growing-ca/ -- Mordvintsev, et al., "Growing Neural Cellular Automata", Distill, 2020) implemented in JAX
Home-page: https://github.com/shyamsn97/jax-nca
Author: Shyam Sudhakaran
Author-email: shyamsnair@protonmail.com
License: MIT
Platform: UNKNOWN
Classifier: Development Status :: 2 - Pre-Alpha
Classifier: License :: OSI Approved :: MIT License
Classifier: Programming Language :: Python :: 3.9
License-File: LICENSE
Requires-Dist: numpy
Requires-Dist: jax
Requires-Dist: flax
Requires-Dist: matplotlib
Requires-Dist: einops
Requires-Dist: tensorflow
Requires-Dist: tensorboardX
Requires-Dist: optax
Requires-Dist: tqdm
Requires-Dist: pandas
Requires-Dist: pillow
Requires-Dist: ipycanvas
Requires-Dist: orjson
Requires-Dist: opencv-python
